zconf/__init__.py
zconf/zconf.py
pyzconf-0.1.2.dist-info/LICENSE
pyzconf-0.1.2.dist-info/WHEEL
pyzconf-0.1.2.dist-info/METADATA
pyzconf-0.1.2.dist-info/RECORD
