Metadata-Version: 2.1
Name: pyzconf
Version: 0.1.2
Summary: 
Author: Doohoon Kim
Author-email: invi.dh.kim@gmail.com
Requires-Python: >=3.10,<4.0
Classifier: Programming Language :: Python :: 3
Classifier: Programming Language :: Python :: 3.10
Classifier: Programming Language :: Python :: 3.11
Requires-Dist: omegaconf (>=2.3.0,<3.0.0)
Requires-Dist: pydfl (>=0.1.0,<0.2.0)
Requires-Dist: python-dotenv (>=1.0.0,<2.0.0)
